CHANGELOG.txt
LICENCE.txt
MANIFEST.in
README.txt
__init__.py
binary_tree.py
breadth_first_search.py
depth_first_search.py
graph.py
maze_template_1.py
node_class.py
setup.py
window.py
DFS_BFS_visualizer.egg-info/PKG-INFO
DFS_BFS_visualizer.egg-info/SOURCES.txt
DFS_BFS_visualizer.egg-info/dependency_links.txt
DFS_BFS_visualizer.egg-info/requires.txt
DFS_BFS_visualizer.egg-info/top_level.txt